tui_progress/__init__.py
tui_progress/collections.py
tui_progress/color.py
tui_progress/itertools.py
tui_progress/progress.py
tui_progress/table.py
tui_progress/terminal.py
tui_progress/tui.py
tui_progress-0.1.1.dist-info/WHEEL
tui_progress-0.1.1.dist-info/METADATA
tui_progress-0.1.1.dist-info/RECORD
