Metadata-Version: 2.1
Name: tui-progress
Version: 0.1.1
Summary: 
Author: Zach Kanzler
Author-email: they4kman@gmail.com
Requires-Python: >=3.8,<4.0
Classifier: Programming Language :: Python :: 3
Classifier: Programming Language :: Python :: 3.10
Classifier: Programming Language :: Python :: 3.8
Classifier: Programming Language :: Python :: 3.9
Requires-Dist: asciimatics (>=1.13.0,<2.0.0)
Requires-Dist: cached-property (>=1.5.2,<2.0.0)
Requires-Dist: cursor (>=1.3.4,<2.0.0)
Requires-Dist: halo (>=0.0.31,<0.0.32)
Requires-Dist: humanize (>=4.0.0,<5.0.0)
Requires-Dist: log-symbols (>=0.0.14,<0.0.15)
Requires-Dist: terminaltables (>=3.1.10,<4.0.0)
Requires-Dist: tqdm (>=4.63.0,<5.0.0)
Requires-Dist: wcwidth (>=0.2.5,<0.3.0)
Requires-Dist: wrapt (>=1.14.0,<2.0.0)
